plutobook.cp311-win_amd64.dll.a
plutobook.cp311-win_amd64.pyd
plutobook-0.0.18.data/platlib/libplutobook-0-704745835310dcfd057d5b1ee757bf55.dll
plutobook-0.0.18.dist-info/DELVEWHEEL
plutobook-0.0.18.dist-info/LICENSE
plutobook-0.0.18.dist-info/METADATA
plutobook-0.0.18.dist-info/RECORD
plutobook-0.0.18.dist-info/WHEEL
