Metadata-Version: 2.1
Name: plutobook
Version: 0.0.18
Summary: Paged HTML rendering library
Author-Email: Samuel Ugochukwu <sammycageagle@gmail.com>
License: MIT License
Requires-Python: >=3.8
